PyQifParser/Account.py
PyQifParser/Category.py
PyQifParser/Classification.py
PyQifParser/PyQifParser.py
PyQifParser/Transaction.py
PyQifParser/__init__.py
PyQifParser/example_program.py
pyqifparser-0.5.dist-info/METADATA
pyqifparser-0.5.dist-info/WHEEL
pyqifparser-0.5.dist-info/top_level.txt
pyqifparser-0.5.dist-info/RECORD
