Metadata-Version: 2.4
Name: PyQifParser
Version: 0.5
Summary: A(nother) Python-based Parser for Quicken / Lexware Finance Manager QIF files.
Home-page: https://github.com/hhessel/PyQIF-Parser
Author: Uwe Ziegenhagen / Packaged by Henrik Hessel
Author-email: Uwe Ziegenhagen / Packaged by Henrik Hessel <hhessel@web.de>
License: MIT
Project-URL: Homepage, https://github.com/hhessel/PyQIF-Parser
Requires-Python: >=3.6
Requires-Dist: pandas<3.0.0,>=1.0.0
Requires-Dist: numpy<2.0.0,>=1.18.0
Dynamic: author
Dynamic: home-page
Dynamic: requires-python
